{
    "os": "Linux-4.18.0-425.19.2.el8_7.x86_64-x86_64-with-glibc2.28",
    "python": "3.9.19",
    "heartbeatAt": "2024-09-06T17:31:38.834065",
    "startedAt": "2024-09-06T17:31:38.675084",
    "docker": null,
    "cuda": null,
    "args": [
        "--local-rank=0",
        "--learning_rate",
        "2e-5",
        "--checkpointing",
        "true",
        "--first_eval",
        "false",
        "--save_best",
        "true",
        "--config",
        "./config/vast/finetune_cfg/finetune-area.json",
        "--pretrain_dir",
        "./output/vast/pretrain_vast",
        "--output_dir",
        "./output/vast/pretrain_vast/downstream/finetuneArea"
    ],
    "state": "running",
    "program": "/leonardo_scratch/fast/IscrC_GenOpt/giordano/VAST/./run.py",
    "codePathLocal": "run.py",
    "codePath": "run.py",
    "git": {
        "remote": "https://github.com/TXH-mercury/VAST.git",
        "commit": "410ca47acf40d4ab098e345b76159df66bc42239"
    },
    "email": null,
    "root": "/leonardo_scratch/fast/IscrC_GenOpt/giordano/VAST",
    "host": "lrdn0789.leonardo.local",
    "username": "gcicchet",
    "executable": "/leonardo/home/userexternal/gcicchet/.conda/envs/vast/bin/python3",
    "cpu_count": 32,
    "cpu_count_logical": 32,
    "cpu_freq": {
        "current": 2618.46403125,
        "min": 800.0,
        "max": 2601.0
    },
    "cpu_freq_per_core": [
        {
            "current": 2590.761,
            "min": 800.0,
            "max": 2601.0
        },
        {
            "current": 2583.682,
            "min": 800.0,
            "max": 2601.0
        },
        {
            "current": 2591.024,
            "min": 800.0,
            "max": 2601.0
        },
        {
            "current": 2601.0,
            "min": 800.0,
            "max": 2601.0
        },
        {
            "current": 2592.851,
            "min": 800.0,
            "max": 2601.0
        },
        {
            "current": 2593.614,
            "min": 800.0,
            "max": 2601.0
        },
        {
            "current": 2597.585,
            "min": 800.0,
            "max": 2601.0
        },
        {
            "current": 2594.682,
            "min": 800.0,
            "max": 2601.0
        },
        {
            "current": 2594.984,
            "min": 800.0,
            "max": 2601.0
        },
        {
            "current": 2595.727,
            "min": 800.0,
            "max": 2601.0
        },
        {
            "current": 2602.44,
            "min": 800.0,
            "max": 2601.0
        },
        {
            "current": 2596.747,
            "min": 800.0,
            "max": 2601.0
        },
        {
            "current": 2597.033,
            "min": 800.0,
            "max": 2601.0
        },
        {
            "current": 2597.769,
            "min": 800.0,
            "max": 2601.0
        },
        {
            "current": 2598.044,
            "min": 800.0,
            "max": 2601.0
        },
        {
            "current": 2598.768,
            "min": 800.0,
            "max": 2601.0
        },
        {
            "current": 2599.05,
            "min": 800.0,
            "max": 2601.0
        },
        {
            "current": 2599.889,
            "min": 800.0,
            "max": 2601.0
        },
        {
            "current": 2600.16,
            "min": 800.0,
            "max": 2601.0
        },
        {
            "current": 2600.871,
            "min": 800.0,
            "max": 2601.0
        },
        {
            "current": 2601.135,
            "min": 800.0,
            "max": 2601.0
        },
        {
            "current": 2601.821,
            "min": 800.0,
            "max": 2601.0
        },
        {
            "current": 2602.096,
            "min": 800.0,
            "max": 2601.0
        },
        {
            "current": 2608.02,
            "min": 800.0,
            "max": 2601.0
        },
        {
            "current": 2608.671,
            "min": 800.0,
            "max": 2601.0
        },
        {
            "current": 2610.419,
            "min": 800.0,
            "max": 2601.0
        },
        {
            "current": 2611.017,
            "min": 800.0,
            "max": 2601.0
        },
        {
            "current": 2614.908,
            "min": 800.0,
            "max": 2601.0
        },
        {
            "current": 2550.212,
            "min": 800.0,
            "max": 2601.0
        },
        {
            "current": 2941.221,
            "min": 800.0,
            "max": 2601.0
        },
        {
            "current": 2887.434,
            "min": 800.0,
            "max": 2601.0
        },
        {
            "current": 2633.702,
            "min": 800.0,
            "max": 2601.0
        }
    ],
    "disk": {
        "/": {
            "total": 8.618766784667969,
            "used": 7.602588653564453
        }
    },
    "gpu": "NVIDIA A100-SXM-64GB",
    "gpu_count": 4,
    "gpu_devices": [
        {
            "name": "NVIDIA A100-SXM-64GB",
            "memory_total": 68719476736
        },
        {
            "name": "NVIDIA A100-SXM-64GB",
            "memory_total": 68719476736
        },
        {
            "name": "NVIDIA A100-SXM-64GB",
            "memory_total": 68719476736
        },
        {
            "name": "NVIDIA A100-SXM-64GB",
            "memory_total": 68719476736
        }
    ],
    "memory": {
        "total": 502.855167388916
    }
}
